bob/__init__.py
bob/learn/__init__.py
bob/learn/em/__init__.py
bob/learn/em/factor_analysis.py
bob/learn/em/gmm.py
bob/learn/em/ivector.py
bob/learn/em/kmeans.py
bob/learn/em/linear_scoring.py
bob/learn/em/utils.py
bob/learn/em/wccn.py
bob/learn/em/whitening.py
bob.learn.em-3.3.1.dist-info/LICENSE
bob.learn.em-3.3.1.dist-info/METADATA
bob.learn.em-3.3.1.dist-info/WHEEL
bob.learn.em-3.3.1.dist-info/top_level.txt
bob.learn.em-3.3.1.dist-info/RECORD
