Metadata-Version: 2.1
Name: bob.learn.em
Version: 3.3.1
Summary: Bindings for EM machines and trainers of Bob
Author-email: Andre Anjos <andre.anjos@idiap.ch>
License: BSD 3-Clause License
Project-URL: documentation, https://www.idiap.ch/software/bob/docs/bob/bob.learn.em/v3.3.1/sphinx/
Project-URL: homepage, https://pypi.org/project/bob.learn.em/
Project-URL: repository, https://gitlab.idiap.ch/bob/bob.learn.em
Project-URL: changelog, https://gitlab.idiap.ch/bob/bob.learn.em/-/releases
Keywords: bob,em,expectation-maximization
Classifier: Framework :: Bob
Classifier: Development Status :: 4 - Beta
Classifier: Intended Audience :: Developers
Classifier: License :: OSI Approved :: BSD License
Classifier: Natural Language :: English
Classifier: Programming Language :: Python
Classifier: Programming Language :: Python :: 3
Classifier: Topic :: Software Development :: Libraries :: Python Modules
Requires-Python: >=3.9
License-File: LICENSE
Requires-Dist: bob ==12.1.1
Requires-Dist: dask ==2024.5.2
Requires-Dist: dask-ml ==2024.3.20
Requires-Dist: h5py ~=3.7
Requires-Dist: numpy ~=1.26
Requires-Dist: scikit-learn ~=1.4
Provides-Extra: doc
Requires-Dist: auto-intersphinx ; extra == 'doc'
Requires-Dist: sphinx ; extra == 'doc'
Requires-Dist: sphinx-rtd-theme ; extra == 'doc'
Requires-Dist: sphinx-autodoc-typehints ; extra == 'doc'
Requires-Dist: sphinxcontrib-programoutput ; extra == 'doc'
Requires-Dist: matplotlib ; extra == 'doc'
Provides-Extra: qa
Requires-Dist: pre-commit ; extra == 'qa'
Provides-Extra: test
Requires-Dist: pytest ; extra == 'test'
Requires-Dist: pytest-cov ; extra == 'test'
Requires-Dist: coverage ; extra == 'test'
